strlen.py
strlen-1.0.4.dist-info/METADATA
strlen-1.0.4.dist-info/WHEEL
strlen-1.0.4.dist-info/RECORD
