Metadata-Version: 2.1
Name: strlen
Version: 1.0.4
Summary: This module allows you to compare strings not by ord() values of chars, but by the length of the string - len()
Author: Romooper
Author-email: romanshupik32@gmail.com
Requires-Python: >=3.6,<4.0
Classifier: Programming Language :: Python :: 3
Classifier: Programming Language :: Python :: 3.6
Classifier: Programming Language :: Python :: 3.7
Classifier: Programming Language :: Python :: 3.8
Classifier: Programming Language :: Python :: 3.9
Classifier: Programming Language :: Python :: 3.10
Classifier: Programming Language :: Python :: 3.11
Classifier: Programming Language :: Python :: 3.12
